litepolis_database_starrocks/Actor.py
litepolis_database_starrocks/Conversations.py
litepolis_database_starrocks/Users.py
litepolis_database_starrocks/__init__.py
litepolis_database_starrocks/utils.py
litepolis_database_starrocks-0.0.1.dist-info/licenses/LICENSE
litepolis_database_starrocks-0.0.1.dist-info/METADATA
litepolis_database_starrocks-0.0.1.dist-info/WHEEL
litepolis_database_starrocks-0.0.1.dist-info/top_level.txt
litepolis_database_starrocks-0.0.1.dist-info/RECORD
