Metadata-Version: 2.4
Name: litepolis-database-starrocks
Version: 0.0.1
Summary: The starrocks database module for LitePolis
Home-page: https://github.com/cplkake
Author: cplkake
License: MIT License
License-File: LICENSE
Requires-Dist: sqlmodel
Requires-Dist: litepolis
Dynamic: author
Dynamic: description
Dynamic: description-content-type
Dynamic: home-page
Dynamic: license
Dynamic: license-file
Dynamic: requires-dist
Dynamic: summary
